ml_genius/__init__.py
ml_genius/dl/__init__.py
ml_genius/ml/__init__.py
ml_genius/ml/classification/__init__.py
ml_genius/ml/classification/components/__init__.py
ml_genius/ml/classification/components/data_ingestion.py
ml_genius/ml/classification/components/data_transformation.py
ml_genius/ml/classification/components/model_trainer.py
ml_genius/ml/classification/entity/__init__.py
ml_genius/ml/classification/entity/artifacts_entity.py
ml_genius/ml/clustering/__init__.py
ml_genius/ml/preprocessor/__init__.py
ml_genius/ml/preprocessor/auto_preprocess.py
ml_genius/ml/preprocessor/datadescriber.py
ml_genius/ml/preprocessor/datareader.py
ml_genius/ml/preprocessor/preprocess.py
ml_genius/ml/preprocessor/processor.py
ml_genius/ml/regression/__init__.py
ml_genius/ml/regression/components/__init__.py
ml_genius/ml/regression/components/data_ingestion.py
ml_genius/ml/regression/components/data_transformation.py
ml_genius/ml/regression/components/model_trainer.py
ml_genius/ml/regression/entity/__init__.py
ml_genius/ml/regression/entity/artifacts_entity.py
ml_genius-0.0.2.dist-info/licenses/LICENSE
ml_genius-0.0.2.dist-info/METADATA
ml_genius-0.0.2.dist-info/WHEEL
ml_genius-0.0.2.dist-info/top_level.txt
ml_genius-0.0.2.dist-info/RECORD
